datasize/__datasize__.py
datasize/__expected_test_results__.py
datasize/__init__.py
datasize/test.py
datasize-0.3.dist-info/DESCRIPTION.rst
datasize-0.3.dist-info/METADATA
datasize-0.3.dist-info/RECORD
datasize-0.3.dist-info/WHEEL
datasize-0.3.dist-info/metadata.json
datasize-0.3.dist-info/top_level.txt
