Metadata-Version: 2.0
Name: datasize
Version: 0.3
Summary: Python integer subclass to handle arithmetic and formatting of integers with data size units
Home-page: https://github.com/aphor/datasize
Author: Jeremy McMillan
Author-email: jeremy.mcmillan@gmail.com
License: UNKNOWN
Download-URL: https://github.com/aphor/datasize/tarball/0.1
Keywords: data,units,parser,formatter
Platform: UNKNOWN
